seaplane_framework/config/__init__.py
seaplane_framework.config-0.0.5.dist-info/LICENSE
seaplane_framework.config-0.0.5.dist-info/METADATA
seaplane_framework.config-0.0.5.dist-info/WHEEL
seaplane_framework.config-0.0.5.dist-info/top_level.txt
seaplane_framework.config-0.0.5.dist-info/RECORD
