Metadata-Version: 2.1
Name: seaplane-framework.config
Version: 0.0.5
Home-page: 
Author: Seaplane IO, Inc.
Author-email: support@seaplane.io
License: Apache 2.0
Keywords: Seaplane,Carrier API
Requires-Python: >=3.8
License-File: LICENSE
Requires-Dist: PyYAML ==6.0.1
